pdem/__init__.py
pdem/pdem.py
pdem-1.0.1.dist-info/licenses/LICENSE
pdem-1.0.1.dist-info/METADATA
pdem-1.0.1.dist-info/WHEEL
pdem-1.0.1.dist-info/entry_points.txt
pdem-1.0.1.dist-info/top_level.txt
pdem-1.0.1.dist-info/RECORD
