Metadata-Version: 2.4
Name: pdem
Version: 1.0.1
Summary: process daemonizer client-server library
Author-email: MihanEntalpo <mihanentalpo@yandex.ru>
License: MIT License
Project-URL: Homepage, https://github.com/MihanEntalpo/pdem
Keywords: run,process,daemonize,monitor,kill,status
Classifier: Development Status :: 4 - Beta
Classifier: Intended Audience :: Developers
Classifier: Intended Audience :: System Administrators
Classifier: Topic :: Software Development :: Libraries
Classifier: Topic :: System :: Monitoring
Classifier: Environment :: Console
Classifier: License :: OSI Approved :: MIT License
Classifier: Programming Language :: Python :: 3 :: Only
Requires-Python: >=3.8
License-File: LICENSE
Requires-Dist: tornado
Dynamic: license-file
